django_cos/__init__.py
django_cos/admin_urls.py
django_cos/fields.py
django_cos/forms.py
django_cos/importexport.py
django_cos/schema.py
django_cos/search_urls.py
django_cos/settings.py
django_cos/urls.py
django_cos/utils.py
django_cos/views.py
django_cos/wagtail_hooks.py
django_cos/widgets.py
django_cos/bin/__init__.py
django_cos/bin/django_cos.py
django_cos/blocks/__init__.py
django_cos/blocks/base_blocks.py
django_cos/blocks/content_blocks.py
django_cos/blocks/html_blocks.py
django_cos/blocks/layout_blocks.py
django_cos/blocks/metadata_blocks.py
django_cos/blocks/mixins.py
django_cos/migrations/0001_initial.py
django_cos/migrations/0002_auto_20180829_1538.py
django_cos/migrations/0003_auto_20180912_1632.py
django_cos/migrations/0004_auto_20181119_1507.py
django_cos/migrations/0005_auto_20181214_2214.py
django_cos/migrations/0006_auto_20181221_2232.py
django_cos/migrations/0007_auto_20181221_2234.py
django_cos/migrations/0008_auto_20181221_2308.py
django_cos/migrations/0009_auto_20181222_2058.py
django_cos/migrations/0010_auto_20181222_2102.py
django_cos/migrations/0011_auto_20181222_2118.py
django_cos/migrations/0012_auto_20181222_2257.py
django_cos/migrations/0013_auto_20181224_1450.py
django_cos/migrations/__init__.py
django_cos/models/__init__.py
django_cos/models/page_models.py
django_cos/models/snippet_models.py
django_cos/models/wagtailsettings_models.py
django_cos/project_template/.gitattributes
django_cos/project_template/Dockerfile
django_cos/project_template/manage.py
django_cos/project_template/requirements.txt
django_cos/project_template/project_name/__init__.py
django_cos/project_template/project_name/urls.py
django_cos/project_template/project_name/wsgi.prod.py
django_cos/project_template/project_name/wsgi.py
django_cos/project_template/project_name/settings/__init__.py
django_cos/project_template/project_name/settings/base.py
django_cos/project_template/project_name/settings/dev.py
django_cos/project_template/project_name/settings/prod.py
django_cos-0.4.0.dist-info/LICENSE
django_cos-0.4.0.dist-info/METADATA
django_cos-0.4.0.dist-info/WHEEL
django_cos-0.4.0.dist-info/entry_points.txt
django_cos-0.4.0.dist-info/top_level.txt
django_cos-0.4.0.dist-info/RECORD
