Metadata-Version: 2.1
Name: django-cos
Version: 0.4.0
Summary: Wagtail-based COS for building efficient marketing websites out the box.
Home-page: https://github.com/ntbrown/django-cos
Author: Nicholas Brown
Author-email: overflow2341313@gmail.com
License: BSD License
Download-URL: https://github.com/ntbrown/django-cos/archive/v0.1.tar.gz
Platform: UNKNOWN
Classifier: Environment :: Web Environment
Classifier: Framework :: Django
Classifier: Intended Audience :: Developers
Classifier: Operating System :: OS Independent
Classifier: Programming Language :: Python
Classifier: Programming Language :: Python :: 3
Classifier: Programming Language :: Python :: 3.4
Classifier: Programming Language :: Python :: 3.5
Classifier: Programming Language :: Python :: 3.6
Classifier: Programming Language :: Python :: 3 :: Only
Classifier: Framework :: Django
Classifier: Framework :: Django :: 2.0
Classifier: Framework :: Wagtail
Classifier: Framework :: Wagtail :: 2
Classifier: Topic :: Internet :: WWW/HTTP
Classifier: Topic :: Internet :: WWW/HTTP :: Dynamic Content
Classifier: Topic :: Internet :: WWW/HTTP :: Site Management
Requires-Dist: django-eventtools (==0.9.*)
Requires-Dist: django-bootstrap4
Requires-Dist: django (<2.2,>=1.11)
Requires-Dist: geocoder (<2.0,>=1.38.1)
Requires-Dist: icalendar (==4.0.*)
Requires-Dist: wagtail (==2.3.*)
Requires-Dist: wagtailfontawesome (<2.0,>=1.1.3)
Requires-Dist: wagtail-cache (==0.2.*)
Requires-Dist: wagtail-import-export (<0.2,>=0.1)
Requires-Dist: wagtail-tag-manager (==0.7.0)
Requires-Dist: wagtail-accessibility (==0.1.2)
Provides-Extra: dev
Requires-Dist: pylint-django ; extra == 'dev'
Requires-Dist: sphinx ; extra == 'dev'
Requires-Dist: twine ; extra == 'dev'
